build/lib/dengdengt/dada.py
dengdengt/dada.py
dengdengt-1.0.2.dist-info/METADATA
dengdengt-1.0.2.dist-info/WHEEL
dengdengt-1.0.2.dist-info/top_level.txt
dengdengt-1.0.2.dist-info/RECORD
