Metadata-Version: 2.1
Name: dengdengt
Version: 1.0.2
Summary: ke_
Author: Dada.cod
Author-email: 626987961@qq.com
License: MIT
Keywords: ke
